{
  "$schema": "http://json-schema.org/draft-04/schema#",
  "type": "object",
  "properties": {
    "hearingId": {
      "$ref": "#/definitions/uuid"
    },
    "hearingEventDefinitionId": {
      "$ref": "#/definitions/uuid"
    },
    "hearingEventId": {
      "$ref": "#/definitions/uuid"
    },
    "latestHearingEventId": {
      "$ref": "#/definitions/uuid"
    },
    "recordedLabel": {
      "type": "string"
    },
    "eventTime": {
      "type": "string",
      "format": "date-time"
    },
    "lastModifiedTime": {
      "type": "string",
      "format": "date-time"
    },
    "alterable": {
      "type": "boolean"
    }
  },
  "additionalProperties": false,
  "required": [
    "hearingId",
    "hearingEventId",
    "latestHearingEventId",
    "recordedLabel",
    "eventTime",
    "lastModifiedTime",
    "alterable"
  ],
  "definitions": {
    "uuid": {
      "type": "string",
      "pattern": "[a-fA-F0-9]{8}-[a-fA-F0-9]{4}-[a-fA-F0-9]{4}-[a-fA-F0-9]{4}-[a-fA-F0-9]{12}$"
    }
  }
}